{"name":"Simulink-Sp15","tagline":"CSE Training Workshops in Engineering Software","body":"## A Short Course for Engineers\r\n##### April 20, 22, 27, 29 (Mon/Wed) • 1–3 p.m. • MEL 1001\r\n\r\nMathWorks Simulink is the premier is a high-powered graphical programming language for modeling and simulating dynamic systems across many domains.  This short course is designed to introduce you to the fundamentals of the interface and modeling through engineering exercises and physical models.\r\n\r\nThis course will be offered in April 2015 by [Computational Science and Engineering](http://cse.illinois.edu/) for a fee of $200, intended to recover costs of course development and delivery.\r\n\r\n<a href=\"http://www.eventbrite.com/e/cse-simulink-workshop-tickets-15759873205?ref=ebtnebregn\" target=\"_blank\"><img src=\"https://www.eventbrite.com/custombutton?eid=15759873205\" alt=\"Eventbrite - CSE Simulink Workshop\" /></a>","google":"UA-53962544-11","note":"Don't delete this file! It's used internally to help with page regeneration."}